MANIFEST.in
README.md
manifest.json
setup.cfg
setup.py
aiovast/__init__.py
aiovast/utils.py
aiovast.egg-info/PKG-INFO
aiovast.egg-info/SOURCES.txt
aiovast.egg-info/dependency_links.txt
aiovast.egg-info/requires.txt
aiovast.egg-info/top_level.txt
aiovast/decorators/__init__.py
aiovast/requests/__init__.py