Metadata-Version: 2.1
Name: aiovast
Version: 4.0.3
Summary: Python3 library to scale functions using asyncio
Home-page: https://github.com/TannerBurns/vast
Author: Tanner Burns
Author-email: tjburns102@gmail.com
License: UNKNOWN
Platform: UNKNOWN
Classifier: Programming Language :: Python :: 3.7
Classifier: Operating System :: OS Independent
